{
    "responses_1": {
        "_id":{"$oid":"7d8b2670e8f6"},
        "surveys_id": "f58b3cf7f999",
        "student_id":"b59fc5b6f09b",
        "professor_rating":4,
        "class_rating":4,
        "default_questions_responses":["No", "No"],
        "professor_made_questions_responses":["No"]
    },
    "responses_3": {
        "_id":{"$oid":"a2a71d962899"},
        "surveys_id": "f58b3cf7f999",
        "student_id":"e4bc4a34bb86",
        "professor_rating":4,
        "class_rating":4,
        "default_questions_responses":["No", "No"],
        "professor_made_questions_responses":["No"]
    },
    "responses_4": {
        "_id":{"$oid":"6866ca233fcb"},
        "surveys_id": "f58b3cf7f999",
        "student_id":"838ff14fdfa2",
        "professor_rating":5,
        "class_rating":3,
        "default_questions_responses":["No", "No"],
        "professor_made_questions_responses":["No"]
    },
    "responses_5": {
        "_id":{"$oid":"4ed031103198"},
        "surveys_id": "f58b3cf7f999",
        "student_id":"c5371846bb3e",
        "professor_rating":4,
        "class_rating":4,
        "default_questions_responses":["No", "No"],
        "professor_made_questions_responses":["No"]
    },
    "responses_6": {
        "_id":{"$oid":"42d4615a9623"},
        "surveys_id": "f58b3cf7f999",
        "student_id":"f5f1d22c0e86",
        "professor_rating":4,
        "class_rating":2,
        "default_questions_responses":["No", "No"],
        "professor_made_questions_responses":["No"]
    },
    "responses_7": {
        "_id":{"$oid":"33f609f1b459"},
        "surveys_id": "f58b3cf7f999",
        "student_id":"035f9a33e75f",
        "professor_rating":4,
        "class_rating":4,
        "default_questions_responses":["No", "No"],
        "professor_made_questions_responses":["No"]
    },
    "responses_8": {
        "_id":{"$oid":"dd6ec71a7d2d"},
        "surveys_id": "f58b3cf7f999",
        "student_id":"50c21b11a53d",
        "professor_rating":1,
        "class_rating":1,
        "default_questions_responses":["No", "No"],
        "professor_made_questions_responses":["No"]
    },
    "responses_9": {
        "_id":{"$oid":"d7b81f1750b4"},
        "surveys_id": "f58b3cf7f999",
        "student_id":"6d25b5c18810",
        "professor_rating":4,
        "class_rating":4,
        "default_questions_responses":["No", "No"],
        "professor_made_questions_responses":["No"]
    },
    "responses_10": {
        "_id":{"$oid":"62cc2a99c269"},
        "surveys_id": "f58b3cf7f999",
        "student_id":"1d416b160603",
        "professor_rating":4,
        "class_rating":4,
        "default_questions_responses":["No", "No"],
        "professor_made_questions_responses":["No"]
    },
    "responses_11": {
        "_id":{"$oid":"6a71a5d88c09"},
        "surveys_id": "f58b3cf7f999",
        "student_id":"7d2561a72c99",
        "professor_rating":4,
        "class_rating":4,
        "default_questions_responses":["No", "No"],
        "professor_made_questions_responses":["No"]
    },
    "responses_12": {
        "_id":{"$oid":"d6f7aee50b83"},
        "surveys_id": "f58b3cf7f999",
        "student_id":"7f64692d71cb",
        "professor_rating":4,
        "class_rating":4,
        "default_questions_responses":["No", "No"],
        "professor_made_questions_responses":["No"]
    },
    "responses_13": {
        "_id":{"$oid":"a896795d3bc3"},
        "surveys_id": "f58b3cf7f999",
        "student_id":"f841fd4998bc",
        "professor_rating":3,
        "class_rating":4,
        "default_questions_responses":["No", "No"],
        "professor_made_questions_responses":["No"]
    },
    "responses_14": {
        "_id":{"$oid":"14f5d84504ff"},
        "surveys_id": "f58b3cf7f999",
        "student_id":"3938b7037c19",
        "professor_rating":4,
        "class_rating":4,
        "default_questions_responses":["No", "No"],
        "professor_made_questions_responses":["No"]
    },
    "responses_15": {
        "_id":{"$oid":"6402242a26ce"},
        "surveys_id": "f58b3cf7f999",
        "student_id":"2303078bec98",
        "professor_rating":4,
        "class_rating":4,
        "default_questions_responses":["No", "No"],
        "professor_made_questions_responses":["No"]
    },
    "responses_16": {
        "_id":{"$oid":"c4c222214e0b"},
        "surveys_id": "f58b3cf7f999",
        "student_id":"f1ac139db07a",
        "professor_rating":4,
        "class_rating":4,
        "default_questions_responses":["No", "No"],
        "professor_made_questions_responses":["No"]
    },
    "responses_17": {
        "_id":{"$oid":"e4c4ff85da6f"},
        "surveys_id": "f58b3cf7f999",
        "student_id":"3adda0712435",
        "professor_rating":4,
        "class_rating":4,
        "default_questions_responses":["No", "No"],
        "professor_made_questions_responses":["No"]
    },
    "responses_18": {
        "_id":{"$oid":"fc1e444d87e3"},
        "surveys_id": "f58b3cf7f999",
        "student_id":"30fdf60564ea",
        "professor_rating":4,
        "class_rating":4,
        "default_questions_responses":["No", "No"],
        "professor_made_questions_responses":["No"]
    },
    "responses_19": {
        "_id":{"$oid":"ad846761dec0"},
        "surveys_id": "f58b3cf7f999",
        "student_id":"85d1f4ba389a",
        "professor_rating":4,
        "class_rating":4,
        "default_questions_responses":["No", "No"],
        "professor_made_questions_responses":["No"]
    },
    "responses_20": {
        "_id":{"$oid":"c0f3ba90d662"},
        "surveys_id": "f58b3cf7f999",
        "student_id":"cb23ab1a317f",
        "professor_rating":4,
        "class_rating":4,
        "default_questions_responses":["No", "No"],
        "professor_made_questions_responses":["No"]
    },







    "responses_21": {
        "_id":{"$oid":"c2de896da85d"},
        "surveys_id": "a65bea4aa69a",
        "student_id":"b59fc5b6f09b",
        "professor_rating":1,
        "class_rating":4,
        "default_questions_responses":["No", "No"],
        "professor_made_questions_responses":[]
    },
    "responses_22": {
        "_id":{"$oid":"6e88b25a7412"},
        "surveys_id": "a65bea4aa69a",
        "student_id":"8eb9c795d226",
        "professor_rating":1,
        "class_rating":4,
        "default_questions_responses":["No", "No"],
        "professor_made_questions_responses":[]
    },
    "responses_23": {
        "_id":{"$oid":"8ec3e22bf7a4"},
        "surveys_id": "a65bea4aa69a",
        "student_id":"e4bc4a34bb86",
        "professor_rating":1,
        "class_rating":4,
        "default_questions_responses":["No", "No"],
        "professor_made_questions_responses":[]
    },
    "responses_24": {
        "_id":{"$oid":"d4d649a63e0a"},
        "surveys_id": "a65bea4aa69a",
        "student_id":"838ff14fdfa2",
        "professor_rating":1,
        "class_rating":4,
        "default_questions_responses":["No", "No"],
        "professor_made_questions_responses":[]
    },
    "responses_26": {
        "_id":{"$oid":"faac5332376c"},
        "surveys_id": "a65bea4aa69a",
        "student_id":"f5f1d22c0e86",
        "professor_rating":1,
        "class_rating":4,
        "default_questions_responses":["No", "No"],
        "professor_made_questions_responses":[]
    },
    "responses_29": {
        "_id":{"$oid":"6e6dfb52c57d"},
        "surveys_id": "a65bea4aa69a",
        "student_id":"6d25b5c18810",
        "professor_rating":1,
        "class_rating":4,
        "default_questions_responses":["No", "No"],
        "professor_made_questions_responses":[]
    },
    "responses_30": {
        "_id":{"$oid":"eb9f2ce6149f"},
        "surveys_id": "a65bea4aa69a",
        "student_id":"1d416b160603",
        "professor_rating":1,
        "class_rating":4,
        "default_questions_responses":["No", "No"],
        "professor_made_questions_responses":[]
    },
    "responses_31": {
        "_id":{"$oid":"8d5b309813c3"},
        "surveys_id": "a65bea4aa69a",
        "student_id":"7d2561a72c99",
        "professor_rating":1,
        "class_rating":4,
        "default_questions_responses":["No", "No"],
        "professor_made_questions_responses":[]
    },
    "responses_32": {
        "_id":{"$oid":"19dff1b3a344"},
        "surveys_id": "a65bea4aa69a",
        "student_id":"7f64692d71cb",
        "professor_rating":1,
        "class_rating":4,
        "default_questions_responses":["No", "No"],
        "professor_made_questions_responses":[]
    },
    "responses_33": {
        "_id":{"$oid":"c2d53d9652b6"},
        "surveys_id": "a65bea4aa69a",
        "student_id":"f841fd4998bc",
        "professor_rating":1,
        "class_rating":4,
        "default_questions_responses":["No", "No"],
        "professor_made_questions_responses":[]
    },
    "responses_34": {
        "_id":{"$oid":"f8bcc354dbec"},
        "surveys_id": "a65bea4aa69a",
        "student_id":"3938b7037c19",
        "professor_rating":1,
        "class_rating":4,
        "default_questions_responses":["No", "No"],
        "professor_made_questions_responses":[]
    },
    "responses_35": {
        "_id":{"$oid":"3a3f94589a0f"},
        "surveys_id": "a65bea4aa69a",
        "student_id":"2303078bec98",
        "professor_rating":1,
        "class_rating":4,
        "default_questions_responses":["No", "No"],
        "professor_made_questions_responses":[]
    },
    "responses_36": {
        "_id":{"$oid":"8dd51a331209"},
        "surveys_id": "a65bea4aa69a",
        "student_id":"f1ac139db07a",
        "professor_rating":1,
        "class_rating":4,
        "default_questions_responses":["No", "No"],
        "professor_made_questions_responses":[]
    },
    "responses_37": {
        "_id":{"$oid":"74b8071468a7"},
        "surveys_id": "a65bea4aa69a",
        "student_id":"3adda0712435",
        "professor_rating":1,
        "class_rating":4,
        "default_questions_responses":["No", "No"],
        "professor_made_questions_responses":[]
    },
    "responses_38": {
        "_id":{"$oid":"ce75bc35e832"},
        "surveys_id": "a65bea4aa69a",
        "student_id":"30fdf60564ea",
        "professor_rating":1,
        "class_rating":4,
        "default_questions_responses":["No", "No"],
        "professor_made_questions_responses":[]
    },
    "responses_39": {
        "_id":{"$oid":"c9d8739d9403"},
        "surveys_id": "a65bea4aa69a",
        "student_id":"85d1f4ba389a",
        "professor_rating":1,
        "class_rating":4,
        "default_questions_responses":["No", "No"],
        "professor_made_questions_responses":[]
    },
    "responses_40": {
        "_id":{"$oid":"f7ba8d4ff818"},
        "surveys_id": "a65bea4aa69a",
        "student_id":"cb23ab1a317f",
        "professor_rating":1,
        "class_rating":4,
        "default_questions_responses":["No", "No"],
        "professor_made_questions_responses":[]
    },





    "responses_41": {
        "_id":{"$oid":"c7ee69a4f0af"},
        "surveys_id": "06010513a510",
        "student_id":"b59fc5b6f09b",
        "professor_rating":4,
        "class_rating":1,
        "default_questions_responses":["No", "No"],
        "professor_made_questions_responses":["No", "Yes"]
    },
    "responses_42": {
        "_id":{"$oid":"b46353595913"},
        "surveys_id": "06010513a510",
        "student_id":"8eb9c795d226",
        "professor_rating":4,
        "class_rating":1,
        "default_questions_responses":["No", "No"],
        "professor_made_questions_responses":["No", "Yes"]
    },
    "responses_43": {
        "_id":{"$oid":"12a309c22344"},
        "surveys_id": "06010513a510",
        "student_id":"e4bc4a34bb86",
        "professor_rating":4,
        "class_rating":1,
        "default_questions_responses":["No", "No"],
        "professor_made_questions_responses":["No", "Yes"]
    },
    "responses_44": {
        "_id":{"$oid":"ee170276460f"},
        "surveys_id": "06010513a510",
        "student_id":"838ff14fdfa2",
        "professor_rating":4,
        "class_rating":1,
        "default_questions_responses":["No", "No"],
        "professor_made_questions_responses":["No", "Yes"]
    },
    "responses_45": {
        "_id":{"$oid":"8ed426f8d901"},
        "surveys_id": "06010513a510",
        "student_id":"c5371846bb3e",
        "professor_rating":4,
        "class_rating":1,
        "default_questions_responses":["No", "No"],
        "professor_made_questions_responses":["No", "Yes"]
    },
    "responses_46": {
        "_id":{"$oid":"f26751eca90a"},
        "surveys_id": "06010513a510",
        "student_id":"f5f1d22c0e86",
        "professor_rating":4,
        "class_rating":1,
        "default_questions_responses":["No", "No"],
        "professor_made_questions_responses":["No", "Yes"]
    },
    "responses_59": {
        "_id":{"$oid":"0c1c63777e57"},
        "surveys_id": "06010513a510",
        "student_id":"85d1f4ba389a",
        "professor_rating":4,
        "class_rating":1,
        "default_questions_responses":["No", "No"],
        "professor_made_questions_responses":["No", "Yes"]
    },
    "responses_60": {
        "_id":{"$oid":"439d585b4bcc"},
        "surveys_id": "06010513a510",
        "student_id":"cb23ab1a317f",
        "professor_rating":4,
        "class_rating":1,
        "default_questions_responses":["No", "No"],
        "professor_made_questions_responses":["No", "Yes"]
    },




    "responses_61": {
        "_id":{"$oid":"08201171a14a"},
        "surveys_id": "a058a426a7fd",
        "student_id":"b59fc5b6f09b",
        "professor_rating":5,
        "class_rating":4,
        "default_questions_responses":["No", "No"],
        "professor_made_questions_responses":["No"]
    },
    "responses_62": {
        "_id":{"$oid":"bf983cf197e7"},
        "surveys_id": "a058a426a7fd",
        "student_id":"8eb9c795d226",
        "professor_rating":5,
        "class_rating":4,
        "default_questions_responses":["No", "No"],
        "professor_made_questions_responses":["No"]
    },
    "responses_63": {
        "_id":{"$oid":"bb3a47f4c765"},
        "surveys_id": "a058a426a7fd",
        "student_id":"e4bc4a34bb86",
        "professor_rating":5,
        "class_rating":4,
        "default_questions_responses":["No", "No"],
        "professor_made_questions_responses":["No"]
    },
    "responses_64": {
        "_id":{"$oid":"125c08b9b30c"},
        "surveys_id": "a058a426a7fd",
        "student_id":"838ff14fdfa2",
        "professor_rating":5,
        "class_rating":4,
        "default_questions_responses":["No", "No"],
        "professor_made_questions_responses":["No"]
    },
    "responses_65": {
        "_id":{"$oid":"9fad5e0565fe"},
        "surveys_id": "a058a426a7fd",
        "student_id":"c5371846bb3e",
        "professor_rating":5,
        "class_rating":4,
        "default_questions_responses":["No", "No"],
        "professor_made_questions_responses":["No"]
    },
    "responses_66": {
        "_id":{"$oid":"7eac0fa8a265"},
        "surveys_id": "a058a426a7fd",
        "student_id":"f5f1d22c0e86",
        "professor_rating":5,
        "class_rating":4,
        "default_questions_responses":["No", "No"],
        "professor_made_questions_responses":["No"]
    },
    "responses_67": {
        "_id":{"$oid":"9d502a380144"},
        "surveys_id": "a058a426a7fd",
        "student_id":"035f9a33e75f",
        "professor_rating":5,
        "class_rating":4,
        "default_questions_responses":["No", "No"],
        "professor_made_questions_responses":["No"]
    },
    "responses_68": {
        "_id":{"$oid":"61d0d2dd3718"},
        "surveys_id": "a058a426a7fd",
        "student_id":"50c21b11a53d",
        "professor_rating":5,
        "class_rating":4,
        "default_questions_responses":["No", "No"],
        "professor_made_questions_responses":["No"]
    },
    "responses_69": {
        "_id":{"$oid":"8a19f3c50a8c"},
        "surveys_id": "a058a426a7fd",
        "student_id":"6d25b5c18810",
        "professor_rating":5,
        "class_rating":4,
        "default_questions_responses":["No", "No"],
        "professor_made_questions_responses":["No"]
    },
    "responses_79": {
        "_id":{"$oid":"4213ca2f009c"},
        "surveys_id": "a058a426a7fd",
        "student_id":"85d1f4ba389a",
        "professor_rating":5,
        "class_rating":4,
        "default_questions_responses":["No", "No"],
        "professor_made_questions_responses":["No"]
    },
    "responses_80": {
        "_id":{"$oid":"94f968a27ad9"},
        "surveys_id": "a058a426a7fd",
        "student_id":"cb23ab1a317f",
        "professor_rating":5,
        "class_rating":4,
        "default_questions_responses":["No", "No"],
        "professor_made_questions_responses":["No"]
    },




    "responses_87": {
        "_id":{"$oid":"3800f4796a99"},
        "surveys_id": "be452dab0e43",
        "student_id":"035f9a33e75f",
        "professor_rating":4,
        "class_rating":4,
        "default_questions_responses":["No", "No"],
        "professor_made_questions_responses":[]
    },
    "responses_88": {
        "_id":{"$oid":"b5aa2a26814b"},
        "surveys_id": "be452dab0e43",
        "student_id":"50c21b11a53d",
        "professor_rating":4,
        "class_rating":4,
        "default_questions_responses":["No", "No"],
        "professor_made_questions_responses":[]
    },
    "responses_89": {
        "_id":{"$oid":"651a3a021dfc"},
        "surveys_id": "be452dab0e43",
        "student_id":"6d25b5c18810",
        "professor_rating":4,
        "class_rating":4,
        "default_questions_responses":["No", "No"],
        "professor_made_questions_responses":[]
    },
    "responses_90": {
        "_id":{"$oid":"e45c9c0482fe"},
        "surveys_id": "be452dab0e43",
        "student_id":"1d416b160603",
        "professor_rating":4,
        "class_rating":4,
        "default_questions_responses":["No", "No"],
        "professor_made_questions_responses":[]
    },
    "responses_91": {
        "_id":{"$oid":"2fa8af3c5f62"},
        "surveys_id": "be452dab0e43",
        "student_id":"7d2561a72c99",
        "professor_rating":4,
        "class_rating":4,
        "default_questions_responses":["No", "No"],
        "professor_made_questions_responses":[]
    },
    "responses_92": {
        "_id":{"$oid":"6025c43c913f"},
        "surveys_id": "be452dab0e43",
        "student_id":"7f64692d71cb",
        "professor_rating":4,
        "class_rating":4,
        "default_questions_responses":["No", "No"],
        "professor_made_questions_responses":[]
    },
    "responses_93": {
        "_id":{"$oid":"4cce5ee9a221"},
        "surveys_id": "be452dab0e43",
        "student_id":"f841fd4998bc",
        "professor_rating":4,
        "class_rating":4,
        "default_questions_responses":["No", "No"],
        "professor_made_questions_responses":[]
    },
    "responses_94": {
        "_id":{"$oid":"a3be570d4741"},
        "surveys_id": "be452dab0e43",
        "student_id":"3938b7037c19",
        "professor_rating":4,
        "class_rating":4,
        "default_questions_responses":["No", "No"],
        "professor_made_questions_responses":[]
    },
    "responses_95": {
        "_id":{"$oid":"5973e0826312"},
        "surveys_id": "be452dab0e43",
        "student_id":"2303078bec98",
        "professor_rating":4,
        "class_rating":4,
        "default_questions_responses":["No", "No"],
        "professor_made_questions_responses":[]
    },
    "responses_96": {
        "_id":{"$oid":"bf0aac3b24f8"},
        "surveys_id": "be452dab0e43",
        "student_id":"f1ac139db07a",
        "professor_rating":4,
        "class_rating":4,
        "default_questions_responses":["No", "No"],
        "professor_made_questions_responses":[]
    },
    "responses_97": {
        "_id":{"$oid":"085f84990383"},
        "surveys_id": "be452dab0e43",
        "student_id":"3adda0712435",
        "professor_rating":4,
        "class_rating":4,
        "default_questions_responses":["No", "No"],
        "professor_made_questions_responses":[]
    },
    "responses_98": {
        "_id":{"$oid":"77f6656d3cd8"},
        "surveys_id": "be452dab0e43",
        "student_id":"30fdf60564ea",
        "professor_rating":4,
        "class_rating":4,
        "default_questions_responses":["No", "No"],
        "professor_made_questions_responses":[]
    },
    "responses_99": {
        "_id":{"$oid":"7f77ff67fb96"},
        "surveys_id": "be452dab0e43",
        "student_id":"85d1f4ba389a",
        "professor_rating":4,
        "class_rating":4,
        "default_questions_responses":["No", "No"],
        "professor_made_questions_responses":[]
    },
    "responses_100": {
        "_id":{"$oid":"b09080f28353"},
        "surveys_id": "be452dab0e43",
        "student_id":"cb23ab1a317f",
        "professor_rating":4,
        "class_rating":4,
        "default_questions_responses":["No", "No"],
        "professor_made_questions_responses":[]
    },




    "responses_101": {
        "_id":{"$oid":"34f18e95e89e"},
        "surveys_id": "d2ffa2b441e7",
        "student_id":"b59fc5b6f09b",
        "professor_rating":4,
        "class_rating":4,
        "default_questions_responses":["No", "No"],
        "professor_made_questions_responses":["No", "yes", "maybe"]
    },
    "responses_102": {
        "_id":{"$oid":"24eae733ac79"},
        "surveys_id": "d2ffa2b441e7",
        "student_id":"8eb9c795d226",
        "professor_rating":4,
        "class_rating":4,
        "default_questions_responses":["No", "No"],
        "professor_made_questions_responses":["No", "yes", "maybe"]
    },
    "responses_103": {
        "_id":{"$oid":"ce0c6ad7bd9c"},
        "surveys_id": "d2ffa2b441e7",
        "student_id":"e4bc4a34bb86",
        "professor_rating":4,
        "class_rating":4,
        "default_questions_responses":["No", "No"],
        "professor_made_questions_responses":["No", "yes", "maybe"]
    },
    "responses_104": {
        "_id":{"$oid":"c0f21d006356"},
        "surveys_id": "d2ffa2b441e7",
        "student_id":"838ff14fdfa2",
        "professor_rating":4,
        "class_rating":4,
        "default_questions_responses":["No", "No"],
        "professor_made_questions_responses":["No", "yes", "maybe"]
    },
    "responses_105": {
        "_id":{"$oid":"3d23e6bf8b9d"},
        "surveys_id": "d2ffa2b441e7",
        "student_id":"c5371846bb3e",
        "professor_rating":4,
        "class_rating":4,
        "default_questions_responses":["No", "No"],
        "professor_made_questions_responses":["No", "yes", "maybe"]
    },
    "responses_106": {
        "_id":{"$oid":"e86bb99505f2"},
        "surveys_id": "d2ffa2b441e7",
        "student_id":"f5f1d22c0e86",
        "professor_rating":4,
        "class_rating":4,
        "default_questions_responses":["No", "No"],
        "professor_made_questions_responses":["No", "yes", "maybe"]
    },
    "responses_107": {
        "_id":{"$oid":"d7bb4dc77e49"},
        "surveys_id": "d2ffa2b441e7",
        "student_id":"035f9a33e75f",
        "professor_rating":4,
        "class_rating":4,
        "default_questions_responses":["No", "No"],
        "professor_made_questions_responses":["No", "yes", "maybe"]
    },
    "responses_113": {
        "_id":{"$oid":"d57eab7ac3dd"},
        "surveys_id": "d2ffa2b441e7",
        "student_id":"f841fd4998bc",
        "professor_rating":4,
        "class_rating":4,
        "default_questions_responses":["No", "No"],
        "professor_made_questions_responses":["No", "yes", "maybe"]
    },
    "responses_114": {
        "_id":{"$oid":"2636919c7461"},
        "surveys_id": "d2ffa2b441e7",
        "student_id":"3938b7037c19",
        "professor_rating":4,
        "class_rating":4,
        "default_questions_responses":["No", "No"],
        "professor_made_questions_responses":["No", "yes", "maybe"]
    },
    "responses_115": {
        "_id":{"$oid":"8c4cd9efdd45"},
        "surveys_id": "d2ffa2b441e7",
        "student_id":"2303078bec98",
        "professor_rating":4,
        "class_rating":4,
        "default_questions_responses":["No", "No"],
        "professor_made_questions_responses":["No", "yes", "maybe"]
    },
    "responses_116": {
        "_id":{"$oid":"2e4b2f8a5ad9"},
        "surveys_id": "d2ffa2b441e7",
        "student_id":"f1ac139db07a",
        "professor_rating":4,
        "class_rating":4,
        "default_questions_responses":["No", "No"],
        "professor_made_questions_responses":["No", "yes", "maybe"]
    },
    "responses_117": {
        "_id":{"$oid":"4cc765c66f6f"},
        "surveys_id": "d2ffa2b441e7",
        "student_id":"3adda0712435",
        "professor_rating":4,
        "class_rating":4,
        "default_questions_responses":["No", "No"],
        "professor_made_questions_responses":["No", "yes", "maybe"]
    },
    "responses_118": {
        "_id":{"$oid":"de04623bfc09"},
        "surveys_id": "d2ffa2b441e7",
        "student_id":"30fdf60564ea",
        "professor_rating":4,
        "class_rating":4,
        "default_questions_responses":["No", "No"],
        "professor_made_questions_responses":["No", "yes", "maybe"]
    },
    "responses_119": {
        "_id":{"$oid":"d18420c60587"},
        "surveys_id": "d2ffa2b441e7",
        "student_id":"85d1f4ba389a",
        "professor_rating":4,
        "class_rating":4,
        "default_questions_responses":["No", "No"],
        "professor_made_questions_responses":["No", "yes", "maybe"]
    },
    "responses_120": {
        "_id":{"$oid":"ee5ae6644336"},
        "surveys_id": "d2ffa2b441e7",
        "student_id":"cb23ab1a317f",
        "professor_rating":4,
        "class_rating":4,
        "default_questions_responses":["No", "No"],
        "professor_made_questions_responses":["No", "yes", "maybe"]
    },




    "responses_140": {
        "_id":{"$oid":"d2a471ab1e32"},
        "surveys_id": "24f17f5585cf",
        "student_id":"cb23ab1a317f",
        "professor_rating":4,
        "class_rating":4,
        "default_questions_responses":["No", "No"],
        "professor_made_questions_responses":["No"]
    },






 
    "responses_177": {
        "_id":{"$oid":"5b687be31639"},
        "surveys_id": "ffba13a07c72",
        "student_id":"3adda0712435",
        "professor_rating":4,
        "class_rating":4,
        "default_questions_responses":["No", "No"],
        "professor_made_questions_responses":[]
    },
    "responses_178": {
        "_id":{"$oid":"cdddef65b600"},
        "surveys_id": "ffba13a07c72",
        "student_id":"30fdf60564ea",
        "professor_rating":4,
        "class_rating":4,
        "default_questions_responses":["No", "No"],
        "professor_made_questions_responses":[]
    },
    "responses_179": {
        "_id":{"$oid":"4e26167c0d38"},
        "surveys_id": "ffba13a07c72",
        "student_id":"85d1f4ba389a",
        "professor_rating":4,
        "class_rating":4,
        "default_questions_responses":["No", "No"],
        "professor_made_questions_responses":[]
    },
    "responses_180": {
        "_id":{"$oid":"1e5c68000053"},
        "surveys_id": "ffba13a07c72",
        "student_id":"cb23ab1a317f",
        "professor_rating":4,
        "class_rating":4,
        "default_questions_responses":["No", "No"],
        "professor_made_questions_responses":[]
    },



    "responses_196": {
        "_id":{"$oid":"f8fe47b2b705"},
        "surveys_id": "0d003d4bac22",
        "student_id":"f1ac139db07a",
        "professor_rating":4,
        "class_rating":4,
        "default_questions_responses":["No", "No"],
        "professor_made_questions_responses":["No", "yes", "Maybe"]
    },
    "responses_197": {
        "_id":{"$oid":"27de0894c140"},
        "surveys_id": "0d003d4bac22",
        "student_id":"3adda0712435",
        "professor_rating":4,
        "class_rating":4,
        "default_questions_responses":["No", "No"],
        "professor_made_questions_responses":["No", "yes", "Maybe"]
    },
    "responses_198": {
        "_id":{"$oid":"7bbcfcdb09a3"},
        "surveys_id": "0d003d4bac22",
        "student_id":"30fdf60564ea",
        "professor_rating":4,
        "class_rating":4,
        "default_questions_responses":["No", "No"],
        "professor_made_questions_responses":["No", "yes", "Maybe"]
    },
    "responses_199": {
        "_id":{"$oid":"36ed3be12bfb"},
        "surveys_id": "0d003d4bac22",
        "student_id":"85d1f4ba389a",
        "professor_rating":4,
        "class_rating":4,
        "default_questions_responses":["No", "No"],
        "professor_made_questions_responses":["No", "yes", "Maybe"]
    },
    "responses_200": {
        "_id":{"$oid":"67c6cfbe738c"},
        "surveys_id": "0d003d4bac22",
        "student_id":"cb23ab1a317f",
        "professor_rating":4,
        "class_rating":4,
        "default_questions_responses":["No", "No"],
        "professor_made_questions_responses":["No", "yes", "Maybe"]
    },







    "responses_211": {
        "_id":{"$oid":"d395863b719b"},
        "surveys_id": "47a19a1a8c97",
        "student_id":"7d2561a72c99",
        "professor_rating":4,
        "class_rating":4,
        "default_questions_responses":["No", "No"],
        "professor_made_questions_responses":["No"]
    },
    "responses_212": {
        "_id":{"$oid":"1a2a8a77078d"},
        "surveys_id": "47a19a1a8c97",
        "student_id":"7f64692d71cb",
        "professor_rating":4,
        "class_rating":4,
        "default_questions_responses":["No", "No"],
        "professor_made_questions_responses":["No"]
    },
    "responses_213": {
        "_id":{"$oid":"73dacaa08b17"},
        "surveys_id": "47a19a1a8c97",
        "student_id":"f841fd4998bc",
        "professor_rating":4,
        "class_rating":4,
        "default_questions_responses":["No", "No"],
        "professor_made_questions_responses":["No"]
    },
    "responses_214": {
        "_id":{"$oid":"b97ab192c1cc"},
        "surveys_id": "47a19a1a8c97",
        "student_id":"3938b7037c19",
        "professor_rating":4,
        "class_rating":4,
        "default_questions_responses":["No", "No"],
        "professor_made_questions_responses":["No"]
    },
    "responses_215": {
        "_id":{"$oid":"5f0d9fbc174a"},
        "surveys_id": "47a19a1a8c97",
        "student_id":"2303078bec98",
        "professor_rating":4,
        "class_rating":4,
        "default_questions_responses":["No", "No"],
        "professor_made_questions_responses":["No"]
    },
    "responses_216": {
        "_id":{"$oid":"8205276cab34"},
        "surveys_id": "47a19a1a8c97",
        "student_id":"f1ac139db07a",
        "professor_rating":4,
        "class_rating":4,
        "default_questions_responses":["No", "No"],
        "professor_made_questions_responses":["No"]
    },
    "responses_217": {
        "_id":{"$oid":"8ffd7b962a71"},
        "surveys_id": "47a19a1a8c97",
        "student_id":"3adda0712435",
        "professor_rating":4,
        "class_rating":4,
        "default_questions_responses":["No", "No"],
        "professor_made_questions_responses":["No"]
    },
    "responses_218": {
        "_id":{"$oid":"714973e3783f"},
        "surveys_id": "47a19a1a8c97",
        "student_id":"30fdf60564ea",
        "professor_rating":4,
        "class_rating":4,
        "default_questions_responses":["No", "No"],
        "professor_made_questions_responses":["No"]
    },
    "responses_219": {
        "_id":{"$oid":"e8ffa542e8ae"},
        "surveys_id": "47a19a1a8c97",
        "student_id":"85d1f4ba389a",
        "professor_rating":4,
        "class_rating":4,
        "default_questions_responses":["No", "No"],
        "professor_made_questions_responses":["No"]
    },
    "responses_220": {
        "_id":{"$oid":"20219e1cc5df"},
        "surveys_id": "47a19a1a8c97",
        "student_id":"cb23ab1a317f",
        "professor_rating":4,
        "class_rating":4,
        "default_questions_responses":["No", "No"],
        "professor_made_questions_responses":["No"]
    },





    "responses_225": {
        "_id":{"$oid":"9e6ef41bacd3"},
        "surveys_id": "1b3c91baf453",
        "student_id":"c5371846bb3e",
        "professor_rating":4,
        "class_rating":4,
        "default_questions_responses":["No", "No"],
        "professor_made_questions_responses":["No", "yes"]
    },
    "responses_226": {
        "_id":{"$oid":"0123742066dd"},
        "surveys_id": "1b3c91baf453",
        "student_id":"f5f1d22c0e86",
        "professor_rating":4,
        "class_rating":4,
        "default_questions_responses":["No", "No"],
        "professor_made_questions_responses":["No", "yes"]
    },
    "responses_227": {
        "_id":{"$oid":"330ee01e4937"},
        "surveys_id": "1b3c91baf453",
        "student_id":"035f9a33e75f",
        "professor_rating":4,
        "class_rating":4,
        "default_questions_responses":["No", "No"],
        "professor_made_questions_responses":["No", "yes"]
    },
    "responses_228": {
        "_id":{"$oid":"bbd7fe579af3"},
        "surveys_id": "1b3c91baf453",
        "student_id":"50c21b11a53d",
        "professor_rating":4,
        "class_rating":4,
        "default_questions_responses":["No", "No"],
        "professor_made_questions_responses":["No", "yes"]
    },
    "responses_229": {
        "_id":{"$oid":"d3ba1b334cc2"},
        "surveys_id": "1b3c91baf453",
        "student_id":"6d25b5c18810",
        "professor_rating":4,
        "class_rating":4,
        "default_questions_responses":["No", "No"],
        "professor_made_questions_responses":["No", "yes"]
    },
    "responses_230": {
        "_id":{"$oid":"126ce1e46a94"},
        "surveys_id": "1b3c91baf453",
        "student_id":"1d416b160603",
        "professor_rating":4,
        "class_rating":4,
        "default_questions_responses":["No", "No"],
        "professor_made_questions_responses":["No", "yes"]
    },
    "responses_231": {
        "_id":{"$oid":"611bf07a0c05"},
        "surveys_id": "1b3c91baf453",
        "student_id":"7d2561a72c99",
        "professor_rating":4,
        "class_rating":4,
        "default_questions_responses":["No", "No"],
        "professor_made_questions_responses":["No", "yes"]
    },
    "responses_232": {
        "_id":{"$oid":"86854e9239bc"},
        "surveys_id": "1b3c91baf453",
        "student_id":"7f64692d71cb",
        "professor_rating":4,
        "class_rating":4,
        "default_questions_responses":["No", "No"],
        "professor_made_questions_responses":["No", "yes"]
    },
    "responses_233": {
        "_id":{"$oid":"03f8070b07ee"},
        "surveys_id": "1b3c91baf453",
        "student_id":"f841fd4998bc",
        "professor_rating":4,
        "class_rating":4,
        "default_questions_responses":["No", "No"],
        "professor_made_questions_responses":["No", "yes"]
    },
    "responses_234": {
        "_id":{"$oid":"33328eb12d4e"},
        "surveys_id": "1b3c91baf453",
        "student_id":"3938b7037c19",
        "professor_rating":4,
        "class_rating":4,
        "default_questions_responses":["No", "No"],
        "professor_made_questions_responses":["No", "yes"]
    },
    "responses_236": {
        "_id":{"$oid":"f8d6e11cf96c"},
        "surveys_id": "1b3c91baf453",
        "student_id":"f1ac139db07a",
        "professor_rating":4,
        "class_rating":4,
        "default_questions_responses":["No", "No"],
        "professor_made_questions_responses":["No", "yes"]
    },
    "responses_237": {
        "_id":{"$oid":"f3a8c350ee21"},
        "surveys_id": "1b3c91baf453",
        "student_id":"3adda0712435",
        "professor_rating":4,
        "class_rating":4,
        "default_questions_responses":["No", "No"],
        "professor_made_questions_responses":["No", "yes"]
    },
    "responses_238": {
        "_id":{"$oid":"5dcb0cc5cc12"},
        "surveys_id": "1b3c91baf453",
        "student_id":"30fdf60564ea",
        "professor_rating":4,
        "class_rating":4,
        "default_questions_responses":["No", "No"],
        "professor_made_questions_responses":["No", "yes"]
    },
    "responses_239": {
        "_id":{"$oid":"f9f286976cb6"},
        "surveys_id": "1b3c91baf453",
        "student_id":"85d1f4ba389a",
        "professor_rating":4,
        "class_rating":4,
        "default_questions_responses":["No", "No"],
        "professor_made_questions_responses":["No", "yes"]
    },
    "responses_240": {
        "_id":{"$oid":"565e8044d47b"},
        "surveys_id": "1b3c91baf453",
        "student_id":"cb23ab1a317f",
        "professor_rating":4,
        "class_rating":4,
        "default_questions_responses":["No", "No"],
        "professor_made_questions_responses":["No", "yes"]
    },








    "responses_241": {
        "_id":{"$oid":"ecb75b4d4a2b"},
        "surveys_id": "8426e36fddc4",
        "student_id":"b59fc5b6f09b",
        "professor_rating":4,
        "class_rating":4,
        "default_questions_responses":["No", "No"],
        "professor_made_questions_responses":["No"]
    },
    "responses_242": {
        "_id":{"$oid":"fe1989d22979"},
        "surveys_id": "8426e36fddc4",
        "student_id":"8eb9c795d226",
        "professor_rating":4,
        "class_rating":4,
        "default_questions_responses":["No", "No"],
        "professor_made_questions_responses":["No"]
    },
    "responses_243": {
        "_id":{"$oid":"bd9dc2a52819"},
        "surveys_id": "8426e36fddc4",
        "student_id":"e4bc4a34bb86",
        "professor_rating":4,
        "class_rating":4,
        "default_questions_responses":["No", "No"],
        "professor_made_questions_responses":["No"]
    },
    "responses_244": {
        "_id":{"$oid":"e2a23da16b42"},
        "surveys_id": "8426e36fddc4",
        "student_id":"838ff14fdfa2",
        "professor_rating":4,
        "class_rating":4,
        "default_questions_responses":["No", "No"],
        "professor_made_questions_responses":["No"]
    },
    "responses_245": {
        "_id":{"$oid":"17378697c44e"},
        "surveys_id": "8426e36fddc4",
        "student_id":"c5371846bb3e",
        "professor_rating":4,
        "class_rating":4,
        "default_questions_responses":["No", "No"],
        "professor_made_questions_responses":["No"]
    },
    "responses_246": {
        "_id":{"$oid":"9b6f1fe8933c"},
        "surveys_id": "8426e36fddc4",
        "student_id":"f5f1d22c0e86",
        "professor_rating":4,
        "class_rating":4,
        "default_questions_responses":["No", "No"],
        "professor_made_questions_responses":["No"]
    },
    "responses_247": {
        "_id":{"$oid":"595329088a55"},
        "surveys_id": "8426e36fddc4",
        "student_id":"035f9a33e75f",
        "professor_rating":4,
        "class_rating":4,
        "default_questions_responses":["No", "No"],
        "professor_made_questions_responses":["No"]
    },
    "responses_248": {
        "_id":{"$oid":"1768c970e918"},
        "surveys_id": "8426e36fddc4",
        "student_id":"50c21b11a53d",
        "professor_rating":4,
        "class_rating":4,
        "default_questions_responses":["No", "No"],
        "professor_made_questions_responses":["No"]
    },
    "responses_249": {
        "_id":{"$oid":"2ca1b1aec074"},
        "surveys_id": "8426e36fddc4",
        "student_id":"6d25b5c18810",
        "professor_rating":4,
        "class_rating":4,
        "default_questions_responses":["No", "No"],
        "professor_made_questions_responses":["No"]
    },
    "responses_250": {
        "_id":{"$oid":"d9f131bae9ec"},
        "surveys_id": "8426e36fddc4",
        "student_id":"1d416b160603",
        "professor_rating":4,
        "class_rating":4,
        "default_questions_responses":["No", "No"],
        "professor_made_questions_responses":["No"]
    },
    "responses_251": {
        "_id":{"$oid":"3b2354347f38"},
        "surveys_id": "8426e36fddc4",
        "student_id":"7d2561a72c99",
        "professor_rating":4,
        "class_rating":4,
        "default_questions_responses":["No", "No"],
        "professor_made_questions_responses":["No"]
    },
    "responses_252": {
        "_id":{"$oid":"f63670c0f926"},
        "surveys_id": "8426e36fddc4",
        "student_id":"7f64692d71cb",
        "professor_rating":4,
        "class_rating":4,
        "default_questions_responses":["No", "No"],
        "professor_made_questions_responses":["No"]
    },
    "responses_253": {
        "_id":{"$oid":"ed244d7b8e42"},
        "surveys_id": "8426e36fddc4",
        "student_id":"f841fd4998bc",
        "professor_rating":4,
        "class_rating":4,
        "default_questions_responses":["No", "No"],
        "professor_made_questions_responses":["No"]
    },
    "responses_254": {
        "_id":{"$oid":"2f32e8f7b218"},
        "surveys_id": "8426e36fddc4",
        "student_id":"3938b7037c19",
        "professor_rating":4,
        "class_rating":4,
        "default_questions_responses":["No", "No"],
        "professor_made_questions_responses":["No"]
    },
    "responses_255": {
        "_id":{"$oid":"68d38c0007a5"},
        "surveys_id": "8426e36fddc4",
        "student_id":"2303078bec98",
        "professor_rating":4,
        "class_rating":4,
        "default_questions_responses":["No", "No"],
        "professor_made_questions_responses":["No"]
    },
    "responses_256": {
        "_id":{"$oid":"5fb95f676028"},
        "surveys_id": "8426e36fddc4",
        "student_id":"f1ac139db07a",
        "professor_rating":4,
        "class_rating":4,
        "default_questions_responses":["No", "No"],
        "professor_made_questions_responses":["No"]
    },
    "responses_257": {
        "_id":{"$oid":"b1907b770a29"},
        "surveys_id": "8426e36fddc4",
        "student_id":"3adda0712435",
        "professor_rating":4,
        "class_rating":4,
        "default_questions_responses":["No", "No"],
        "professor_made_questions_responses":["No"]
    },
    "responses_258": {
        "_id":{"$oid":"d4fb00c064e8"},
        "surveys_id": "8426e36fddc4",
        "student_id":"30fdf60564ea",
        "professor_rating":4,
        "class_rating":4,
        "default_questions_responses":["No", "No"],
        "professor_made_questions_responses":["No"]
    },
    "responses_259": {
        "_id":{"$oid":"98e8f27b40ce"},
        "surveys_id": "8426e36fddc4",
        "student_id":"85d1f4ba389a",
        "professor_rating":4,
        "class_rating":4,
        "default_questions_responses":["No", "No"],
        "professor_made_questions_responses":["No"]
    },
    "responses_260": {
        "_id":{"$oid":"83438884587e"},
        "surveys_id": "8426e36fddc4",
        "student_id":"cb23ab1a317f",
        "professor_rating":4,
        "class_rating":4,
        "default_questions_responses":["No", "No"],
        "professor_made_questions_responses":["No"]
    },









    "responses_268": {
        "_id":{"$oid":"2d02d1614558"},
        "surveys_id": "1cbb9d4e369f",
        "student_id":"50c21b11a53d",
        "professor_rating":4,
        "class_rating":4,
        "default_questions_responses":["No", "No"],
        "professor_made_questions_responses":["No", "yes", "Maybe"]
    },
    "responses_269": {
        "_id":{"$oid":"78cc08fc9ff6"},
        "surveys_id": "1cbb9d4e369f",
        "student_id":"6d25b5c18810",
        "professor_rating":4,
        "class_rating":4,
        "default_questions_responses":["No", "No"],
        "professor_made_questions_responses":["No", "yes", "Maybe"]
    },
    "responses_270": {
        "_id":{"$oid":"ed67d6a8244c"},
        "surveys_id": "1cbb9d4e369f",
        "student_id":"1d416b160603",
        "professor_rating":4,
        "class_rating":4,
        "default_questions_responses":["No", "No"],
        "professor_made_questions_responses":["No", "yes", "Maybe"]
    },
    "responses_271": {
        "_id":{"$oid":"3a1d6f97311f"},
        "surveys_id": "1cbb9d4e369f",
        "student_id":"7d2561a72c99",
        "professor_rating":4,
        "class_rating":4,
        "default_questions_responses":["No", "No"],
        "professor_made_questions_responses":["No", "yes", "Maybe"]
    },
    "responses_272": {
        "_id":{"$oid":"48089ed17cc9"},
        "surveys_id": "1cbb9d4e369f",
        "student_id":"7f64692d71cb",
        "professor_rating":4,
        "class_rating":4,
        "default_questions_responses":["No", "No"],
        "professor_made_questions_responses":["No", "yes", "Maybe"]
    },
    "responses_273": {
        "_id":{"$oid":"4f777fce9317"},
        "surveys_id": "1cbb9d4e369f",
        "student_id":"f841fd4998bc",
        "professor_rating":4,
        "class_rating":4,
        "default_questions_responses":["No", "No"],
        "professor_made_questions_responses":["No", "yes", "Maybe"]
    },
    "responses_274": {
        "_id":{"$oid":"b086fb9efe9c"},
        "surveys_id": "1cbb9d4e369f",
        "student_id":"3938b7037c19",
        "professor_rating":4,
        "class_rating":4,
        "default_questions_responses":["No", "No"],
        "professor_made_questions_responses":["No", "yes", "Maybe"]
    },
    "responses_275": {
        "_id":{"$oid":"b7af7342793f"},
        "surveys_id": "1cbb9d4e369f",
        "student_id":"2303078bec98",
        "professor_rating":4,
        "class_rating":4,
        "default_questions_responses":["No", "No"],
        "professor_made_questions_responses":["No", "yes", "Maybe"]
    },
    "responses_276": {
        "_id":{"$oid":"f5f137ee64b5"},
        "surveys_id": "1cbb9d4e369f",
        "student_id":"f1ac139db07a",
        "professor_rating":4,
        "class_rating":4,
        "default_questions_responses":["No", "No"],
        "professor_made_questions_responses":["No", "yes", "Maybe"]
    },
    "responses_277": {
        "_id":{"$oid":"75b64f54fd08"},
        "surveys_id": "1cbb9d4e369f",
        "student_id":"3adda0712435",
        "professor_rating":4,
        "class_rating":4,
        "default_questions_responses":["No", "No"],
        "professor_made_questions_responses":["No", "yes", "Maybe"]
    },
    "responses_278": {
        "_id":{"$oid":"e2c5fff41a76"},
        "surveys_id": "1cbb9d4e369f",
        "student_id":"30fdf60564ea",
        "professor_rating":4,
        "class_rating":4,
        "default_questions_responses":["No", "No"],
        "professor_made_questions_responses":["No", "yes", "Maybe"]
    },
    "responses_279": {
        "_id":{"$oid":"c35818d286b2"},
        "surveys_id": "1cbb9d4e369f",
        "student_id":"85d1f4ba389a",
        "professor_rating":4,
        "class_rating":4,
        "default_questions_responses":["No", "No"],
        "professor_made_questions_responses":["No", "yes", "Maybe"]
    },
    "responses_280": {
        "_id":{"$oid":"5e2973aebf96"},
        "surveys_id": "1cbb9d4e369f",
        "student_id":"cb23ab1a317f",
        "professor_rating":4,
        "class_rating":4,
        "default_questions_responses":["No", "No"],
        "professor_made_questions_responses":["No", "yes", "Maybe"]
    },









    "responses_281": {
        "_id":{"$oid":"faf98d2e023c"},
        "surveys_id": "995856cdc212",
        "student_id":"b59fc5b6f09b",
        "professor_rating":4,
        "class_rating":4,
        "default_questions_responses":["No", "No"],
        "professor_made_questions_responses":["No"]
    },
    "responses_282": {
        "_id":{"$oid":"489af1612f16"},
        "surveys_id": "995856cdc212",
        "student_id":"8eb9c795d226",
        "professor_rating":4,
        "class_rating":4,
        "default_questions_responses":["No", "No"],
        "professor_made_questions_responses":["No"]
    },
    "responses_283": {
        "_id":{"$oid":"8b72b2f126a9"},
        "surveys_id": "995856cdc212",
        "student_id":"e4bc4a34bb86",
        "professor_rating":4,
        "class_rating":4,
        "default_questions_responses":["No", "No"],
        "professor_made_questions_responses":["No"]
    },
    "responses_286": {
        "_id":{"$oid":"421223a98259"},
        "surveys_id": "995856cdc212",
        "student_id":"f5f1d22c0e86",
        "professor_rating":4,
        "class_rating":4,
        "default_questions_responses":["No", "No"],
        "professor_made_questions_responses":["No"]
    },
    "responses_287": {
        "_id":{"$oid":"db4671bcc50d"},
        "surveys_id": "995856cdc212",
        "student_id":"035f9a33e75f",
        "professor_rating":4,
        "class_rating":4,
        "default_questions_responses":["No", "No"],
        "professor_made_questions_responses":["No"]
    },
    "responses_288": {
        "_id":{"$oid":"c4f95a4822b2"},
        "surveys_id": "995856cdc212",
        "student_id":"50c21b11a53d",
        "professor_rating":4,
        "class_rating":4,
        "default_questions_responses":["No", "No"],
        "professor_made_questions_responses":["No"]
    },
    "responses_289": {
        "_id":{"$oid":"aae732427582"},
        "surveys_id": "995856cdc212",
        "student_id":"6d25b5c18810",
        "professor_rating":4,
        "class_rating":4,
        "default_questions_responses":["No", "No"],
        "professor_made_questions_responses":["No"]
    },
    "responses_290": {
        "_id":{"$oid":"4df68e1e5a77"},
        "surveys_id": "995856cdc212",
        "student_id":"1d416b160603",
        "professor_rating":4,
        "class_rating":4,
        "default_questions_responses":["No", "No"],
        "professor_made_questions_responses":["No"]
    },
    "responses_291": {
        "_id":{"$oid":"ec65fb6cd8fd"},
        "surveys_id": "995856cdc212",
        "student_id":"7d2561a72c99",
        "professor_rating":4,
        "class_rating":4,
        "default_questions_responses":["No", "No"],
        "professor_made_questions_responses":["No"]
    },
    "responses_292": {
        "_id":{"$oid":"4e589a32f10f"},
        "surveys_id": "995856cdc212",
        "student_id":"7f64692d71cb",
        "professor_rating":4,
        "class_rating":4,
        "default_questions_responses":["No", "No"],
        "professor_made_questions_responses":["No"]
    },
    "responses_293": {
        "_id":{"$oid":"ec5fd54fe73a"},
        "surveys_id": "995856cdc212",
        "student_id":"f841fd4998bc",
        "professor_rating":4,
        "class_rating":4,
        "default_questions_responses":["No", "No"],
        "professor_made_questions_responses":["No"]
    },
    "responses_294": {
        "_id":{"$oid":"31c8284825fb"},
        "surveys_id": "995856cdc212",
        "student_id":"3938b7037c19",
        "professor_rating":4,
        "class_rating":4,
        "default_questions_responses":["No", "No"],
        "professor_made_questions_responses":["No"]
    },
    "responses_295": {
        "_id":{"$oid":"426056707674"},
        "surveys_id": "995856cdc212",
        "student_id":"2303078bec98",
        "professor_rating":4,
        "class_rating":4,
        "default_questions_responses":["No", "No"],
        "professor_made_questions_responses":["No"]
    },
    "responses_296": {
        "_id":{"$oid":"4cf8caffbf27"},
        "surveys_id": "995856cdc212",
        "student_id":"f1ac139db07a",
        "professor_rating":4,
        "class_rating":4,
        "default_questions_responses":["No", "No"],
        "professor_made_questions_responses":["No"]
    },
    "responses_297": {
        "_id":{"$oid":"d918adbf77fc"},
        "surveys_id": "995856cdc212",
        "student_id":"3adda0712435",
        "professor_rating":4,
        "class_rating":4,
        "default_questions_responses":["No", "No"],
        "professor_made_questions_responses":["No"]
    },
    "responses_298": {
        "_id":{"$oid":"9f1a4dbace01"},
        "surveys_id": "995856cdc212",
        "student_id":"30fdf60564ea",
        "professor_rating":4,
        "class_rating":4,
        "default_questions_responses":["No", "No"],
        "professor_made_questions_responses":["No"]
    },
    "responses_299": {
        "_id":{"$oid":"0c02a127424f"},
        "surveys_id": "995856cdc212",
        "student_id":"85d1f4ba389a",
        "professor_rating":4,
        "class_rating":4,
        "default_questions_responses":["No", "No"],
        "professor_made_questions_responses":["No"]
    },
    "responses_300": {
        "_id":{"$oid":"fa6dc0b34a3e"},
        "surveys_id": "995856cdc212",
        "student_id":"cb23ab1a317f",
        "professor_rating":4,
        "class_rating":4,
        "default_questions_responses":["No", "No"],
        "professor_made_questions_responses":["No"]
    },



    "responses_315": {
        "_id":{"$oid":"ef110a02fec2"},
        "surveys_id": "7bd2ec7053cf",
        "student_id":"2303078bec98",
        "professor_rating":4,
        "class_rating":4,
        "default_questions_responses":["No", "No"],
        "professor_made_questions_responses":["No", "yes"]
    },
    "responses_316": {
        "_id":{"$oid":"1ca3f5447fe1"},
        "surveys_id": "7bd2ec7053cf",
        "student_id":"f1ac139db07a",
        "professor_rating":4,
        "class_rating":4,
        "default_questions_responses":["No", "No"],
        "professor_made_questions_responses":["No", "yes"]
    },
    "responses_317": {
        "_id":{"$oid":"5332ce3977ec"},
        "surveys_id": "7bd2ec7053cf",
        "student_id":"3adda0712435",
        "professor_rating":4,
        "class_rating":4,
        "default_questions_responses":["No", "No"],
        "professor_made_questions_responses":["No", "yes"]
    },
    "responses_318": {
        "_id":{"$oid":"fec2e2b9af62"},
        "surveys_id": "7bd2ec7053cf",
        "student_id":"30fdf60564ea",
        "professor_rating":4,
        "class_rating":4,
        "default_questions_responses":["No", "No"],
        "professor_made_questions_responses":["No", "yes"]
    },
    "responses_319": {
        "_id":{"$oid":"7a59c7ba6de9"},
        "surveys_id": "7bd2ec7053cf",
        "student_id":"85d1f4ba389a",
        "professor_rating":4,
        "class_rating":4,
        "default_questions_responses":["No", "No"],
        "professor_made_questions_responses":["No", "yes"]
    },
    "responses_320": {
        "_id":{"$oid":"c2bdcd3c38e3"},
        "surveys_id": "7bd2ec7053cf",
        "student_id":"cb23ab1a317f",
        "professor_rating":4,
        "class_rating":4,
        "default_questions_responses":["No", "No"],
        "professor_made_questions_responses":["No", "yes"]
    },






    "responses_328": {
        "_id":{"$oid":"474fba685a81"},
        "surveys_id": "edeb64f014c7",
        "student_id":"50c21b11a53d",
        "professor_rating":4,
        "class_rating":4,
        "default_questions_responses":["No", "No"],
        "professor_made_questions_responses":["No"]
    },
    "responses_329": {
        "_id":{"$oid":"df5685b8d5f1"},
        "surveys_id": "edeb64f014c7",
        "student_id":"6d25b5c18810",
        "professor_rating":4,
        "class_rating":4,
        "default_questions_responses":["No", "No"],
        "professor_made_questions_responses":["No"]
    },
    "responses_330": {
        "_id":{"$oid":"740d1dfd7f0f"},
        "surveys_id": "edeb64f014c7",
        "student_id":"1d416b160603",
        "professor_rating":4,
        "class_rating":4,
        "default_questions_responses":["No", "No"],
        "professor_made_questions_responses":["No"]
    },
    "responses_331": {
        "_id":{"$oid":"44672b966c55"},
        "surveys_id": "edeb64f014c7",
        "student_id":"7d2561a72c99",
        "professor_rating":4,
        "class_rating":4,
        "default_questions_responses":["No", "No"],
        "professor_made_questions_responses":["No"]
    },
    "responses_332": {
        "_id":{"$oid":"823df55dd4aa"},
        "surveys_id": "edeb64f014c7",
        "student_id":"7f64692d71cb",
        "professor_rating":4,
        "class_rating":4,
        "default_questions_responses":["No", "No"],
        "professor_made_questions_responses":["No"]
    },
    "responses_333": {
        "_id":{"$oid":"89951310e18d"},
        "surveys_id": "edeb64f014c7",
        "student_id":"f841fd4998bc",
        "professor_rating":4,
        "class_rating":4,
        "default_questions_responses":["No", "No"],
        "professor_made_questions_responses":["No"]
    },
    "responses_334": {
        "_id":{"$oid":"45d10b484087"},
        "surveys_id": "edeb64f014c7",
        "student_id":"3938b7037c19",
        "professor_rating":4,
        "class_rating":4,
        "default_questions_responses":["No", "No"],
        "professor_made_questions_responses":["No"]
    },
    "responses_335": {
        "_id":{"$oid":"f18cc14c5b3e"},
        "surveys_id": "edeb64f014c7",
        "student_id":"2303078bec98",
        "professor_rating":4,
        "class_rating":4,
        "default_questions_responses":["No", "No"],
        "professor_made_questions_responses":["No"]
    },
    "responses_336": {
        "_id":{"$oid":"c3f962b3af74"},
        "surveys_id": "edeb64f014c7",
        "student_id":"f1ac139db07a",
        "professor_rating":4,
        "class_rating":4,
        "default_questions_responses":["No", "No"],
        "professor_made_questions_responses":["No"]
    },
    "responses_337": {
        "_id":{"$oid":"a105e5e7968e"},
        "surveys_id": "edeb64f014c7",
        "student_id":"3adda0712435",
        "professor_rating":4,
        "class_rating":4,
        "default_questions_responses":["No", "No"],
        "professor_made_questions_responses":["No"]
    },
    "responses_338": {
        "_id":{"$oid":"b7ebe2275470"},
        "surveys_id": "edeb64f014c7",
        "student_id":"30fdf60564ea",
        "professor_rating":4,
        "class_rating":4,
        "default_questions_responses":["No", "No"],
        "professor_made_questions_responses":["No"]
    },
    "responses_339": {
        "_id":{"$oid":"51be36519a32"},
        "surveys_id": "edeb64f014c7",
        "student_id":"85d1f4ba389a",
        "professor_rating":4,
        "class_rating":4,
        "default_questions_responses":["No", "No"],
        "professor_made_questions_responses":["No"]
    },
    "responses_340": {
        "_id":{"$oid":"6681361a1a1a"},
        "surveys_id": "edeb64f014c7",
        "student_id":"cb23ab1a317f",
        "professor_rating":4,
        "class_rating":4,
        "default_questions_responses":["No", "No"],
        "professor_made_questions_responses":["No"]
    }


}
